lpfics/__init__.py
lpfics/lpfics.py
lpfics/prefered_lpfics.py
LPFICS-0.0.1.dist-info/AUTHORS.rst
LPFICS-0.0.1.dist-info/LICENSE.mit
LPFICS-0.0.1.dist-info/METADATA
LPFICS-0.0.1.dist-info/WHEEL
LPFICS-0.0.1.dist-info/top_level.txt
LPFICS-0.0.1.dist-info/RECORD
