Metadata-Version: 2.1
Name: LPFICS
Version: 0.0.1
Summary: LPFICS aims to enable to find ONE infeasible constraint set if a model is considered infeasible once resolved
Home-page: UNKNOWN
Author: Guillaume VERGER, Lou MORRIET
Author-email: omegalpes-users@groupes.renater.fr
License: UNKNOWN
Platform: UNKNOWN
Classifier: Programming Language :: Python
Classifier: License :: OSI Approved :: MIT License
Classifier: Programming Language :: Python :: 3.6
Classifier: Topic :: Software Development :: Debuggers
Requires-Dist: PuLP (>=1.6.10)
